{"TESTS/samples/comprehensive-issues/auth_service.py": [{"type": "function", "rank": "D", "name": "validate_and_process_user_input", "lineno": 29, "endline": 97, "col_offset": 0, "complexity": 25, "closures": []}, {"type": "class", "rank": "A", "name": "AuthManager", "lineno": 120, "endline": 131, "col_offset": 0, "complexity": 2, "methods": [{"type": "method", "rank": "A", "name": "validate_token", "lineno": 123, "endline": 127, "classname": "AuthManager", "col_offset": 4, "complexity": 1, "closures": []}, {"type": "method", "rank": "A", "name": "hash_password", "lineno": 129, "endline": 131, "classname": "AuthManager", "col_offset": 4, "complexity": 1, "closures": []}]}, {"type": "function", "rank": "A", "name": "authenticate_user", "lineno": 10, "endline": 26, "col_offset": 0, "complexity": 1, "closures": []}, {"type": "function", "rank": "A", "name": "store_user_sessions", "lineno": 100, "endline": 106, "col_offset": 0, "complexity": 1, "closures": []}, {"type": "function", "rank": "A", "name": "bad_function", "lineno": 112, "endline": 115, "col_offset": 0, "complexity": 1, "closures": []}, {"type": "class", "rank": "A", "name": "badName", "lineno": 117, "endline": 118, "col_offset": 0, "complexity": 1, "methods": []}, {"type": "method", "rank": "A", "name": "validate_token", "lineno": 123, "endline": 127, "classname": "AuthManager", "col_offset": 4, "complexity": 1, "closures": []}, {"type": "method", "rank": "A", "name": "hash_password", "lineno": 129, "endline": 131, "classname": "AuthManager", "col_offset": 4, "complexity": 1, "closures": []}], "TESTS/samples/comprehensive-issues/payment_processor.py": [{"type": "function", "rank": "C", "name": "process_complex_payment", "lineno": 41, "endline": 95, "col_offset": 0, "complexity": 19, "closures": []}, {"type": "function", "rank": "A", "name": "calculate_discount_premium", "lineno": 7, "endline": 24, "col_offset": 0, "complexity": 5, "closures": []}, {"type": "function", "rank": "A", "name": "validate_payment_card", "lineno": 27, "endline": 38, "col_offset": 0, "complexity": 3, "closures": []}], "TESTS/samples/comprehensive-issues/style_violations.py": [{"type": "class", "rank": "A", "name": "badClassName", "lineno": 18, "endline": 20, "col_offset": 0, "complexity": 2, "methods": [{"type": "method", "rank": "A", "name": "__init__", "lineno": 19, "endline": 20, "classname": "badClassName", "col_offset": 4, "complexity": 1, "closures": []}]}, {"type": "function", "rank": "A", "name": "thisIsABadFunctionName", "lineno": 11, "endline": 15, "col_offset": 0, "complexity": 1, "closures": []}, {"type": "function", "rank": "A", "name": "function_without_docstring", "lineno": 23, "endline": 24, "col_offset": 0, "complexity": 1, "closures": []}, {"type": "function", "rank": "A", "name": "another_function_with_extremely_long_line_that_should_trigger_style_warning", "lineno": 27, "endline": 30, "col_offset": 0, "complexity": 1, "closures": []}, {"type": "function", "rank": "A", "name": "MixedCaseFunction", "lineno": 36, "endline": 39, "col_offset": 0, "complexity": 1, "closures": []}, {"type": "method", "rank": "A", "name": "__init__", "lineno": 19, "endline": 20, "classname": "badClassName", "col_offset": 4, "complexity": 1, "closures": []}], "TESTS/samples/comprehensive-issues/database_queries.py": [{"type": "function", "rank": "A", "name": "search_users_by_name", "lineno": 8, "endline": 20, "col_offset": 0, "complexity": 1, "closures": []}, {"type": "function", "rank": "A", "name": "delete_user_account", "lineno": 23, "endline": 30, "col_offset": 0, "complexity": 1, "closures": []}, {"type": "function", "rank": "A", "name": "update_user_email", "lineno": 33, "endline": 40, "col_offset": 0, "complexity": 1, "closures": []}, {"type": "function", "rank": "A", "name": "execute_custom_query", "lineno": 43, "endline": 49, "col_offset": 0, "complexity": 1, "closures": []}], "TESTS/samples/comprehensive-issues/email_templates.py": [{"type": "class", "rank": "A", "name": "badClassName", "lineno": 37, "endline": 40, "col_offset": 0, "complexity": 2, "methods": [{"type": "method", "rank": "A", "name": "__init__", "lineno": 39, "endline": 40, "classname": "badClassName", "col_offset": 4, "complexity": 1, "closures": []}]}, {"type": "function", "rank": "A", "name": "generate_welcome_email_with_user_info_and_personalization_and_marketing_links_and_tracking", "lineno": 11, "endline": 17, "col_offset": 0, "complexity": 1, "closures": []}, {"type": "function", "rank": "A", "name": "send_notification", "lineno": 20, "endline": 25, "col_offset": 0, "complexity": 1, "closures": []}, {"type": "function", "rank": "A", "name": "x", "lineno": 32, "endline": 34, "col_offset": 0, "complexity": 1, "closures": []}, {"type": "function", "rank": "A", "name": "another_function_with_many_params", "lineno": 43, "endline": 47, "col_offset": 0, "complexity": 1, "closures": []}, {"type": "method", "rank": "A", "name": "__init__", "lineno": 39, "endline": 40, "classname": "badClassName", "col_offset": 4, "complexity": 1, "closures": []}], "TESTS/samples/comprehensive-issues/subscription_manager.py": [{"type": "function", "rank": "A", "name": "calculate_subscription_price", "lineno": 7, "endline": 26, "col_offset": 0, "complexity": 5, "closures": []}, {"type": "function", "rank": "A", "name": "validate_credit_card_details", "lineno": 29, "endline": 40, "col_offset": 0, "complexity": 3, "closures": []}, {"type": "function", "rank": "A", "name": "create_subscription", "lineno": 43, "endline": 50, "col_offset": 0, "complexity": 1, "closures": []}], "TESTS/samples/comprehensive-issues/data_export.py": [{"type": "function", "rank": "A", "name": "export_users_to_csv", "lineno": 12, "endline": 17, "col_offset": 0, "complexity": 2, "closures": []}, {"type": "class", "rank": "A", "name": "UnusedExporter", "lineno": 39, "endline": 47, "col_offset": 0, "complexity": 2, "methods": [{"type": "method", "rank": "A", "name": "__init__", "lineno": 43, "endline": 44, "classname": "UnusedExporter", "col_offset": 4, "complexity": 1, "closures": []}, {"type": "method", "rank": "A", "name": "export", "lineno": 46, "endline": 47, "classname": "UnusedExporter", "col_offset": 4, "complexity": 1, "closures": []}]}, {"type": "function", "rank": "A", "name": "unused_export_function", "lineno": 20, "endline": 24, "col_offset": 0, "complexity": 1, "closures": []}, {"type": "function", "rank": "A", "name": "format_user_data", "lineno": 27, "endline": 36, "col_offset": 0, "complexity": 1, "closures": []}, {"type": "function", "rank": "A", "name": "another_dead_function", "lineno": 50, "endline": 56, "col_offset": 0, "complexity": 1, "closures": []}, {"type": "method", "rank": "A", "name": "__init__", "lineno": 43, "endline": 44, "classname": "UnusedExporter", "col_offset": 4, "complexity": 1, "closures": []}, {"type": "method", "rank": "A", "name": "export", "lineno": 46, "endline": 47, "classname": "UnusedExporter", "col_offset": 4, "complexity": 1, "closures": []}]}
